QuyueDeGongxuRuheLijieYouxi/README.md
QuyueDeGongxuRuheLijieYouxi/__init__.py
QuyueDeGongxuRuheLijieYouxi/__main__.py
QuyueDeGongxuRuheLijieYouxi/file.epub
QuyueDeGongxuRuheLijieYouxi/index.html
QuyueDeGongxuRuheLijieYouxi/css/__init__.py
QuyueDeGongxuRuheLijieYouxi/css/annotations.css
QuyueDeGongxuRuheLijieYouxi/css/main.css
QuyueDeGongxuRuheLijieYouxi/css/normalize.css
QuyueDeGongxuRuheLijieYouxi/css/popup.css
QuyueDeGongxuRuheLijieYouxi/font/__init__.py
QuyueDeGongxuRuheLijieYouxi/font/fontello.eot
QuyueDeGongxuRuheLijieYouxi/font/fontello.svg
QuyueDeGongxuRuheLijieYouxi/font/fontello.ttf
QuyueDeGongxuRuheLijieYouxi/font/fontello.woff
QuyueDeGongxuRuheLijieYouxi/img/__init__.py
QuyueDeGongxuRuheLijieYouxi/img/annotator-glyph-sprite.png
QuyueDeGongxuRuheLijieYouxi/img/annotator-icon-sprite.png
QuyueDeGongxuRuheLijieYouxi/img/apple-touch-icon.png
QuyueDeGongxuRuheLijieYouxi/img/cancelfullscreen.png
QuyueDeGongxuRuheLijieYouxi/img/close.png
QuyueDeGongxuRuheLijieYouxi/img/fullscreen.png
QuyueDeGongxuRuheLijieYouxi/img/loader.gif
QuyueDeGongxuRuheLijieYouxi/img/menu-icon.png
QuyueDeGongxuRuheLijieYouxi/img/save.png
QuyueDeGongxuRuheLijieYouxi/img/saved.png
QuyueDeGongxuRuheLijieYouxi/img/settings-s.png
QuyueDeGongxuRuheLijieYouxi/img/settings.png
QuyueDeGongxuRuheLijieYouxi/img/star.png
QuyueDeGongxuRuheLijieYouxi/js/__init__.py
QuyueDeGongxuRuheLijieYouxi/js/epub.js
QuyueDeGongxuRuheLijieYouxi/js/epub.min.js
QuyueDeGongxuRuheLijieYouxi/js/epub.min.map
QuyueDeGongxuRuheLijieYouxi/js/hooks.min.js
QuyueDeGongxuRuheLijieYouxi/js/hooks.min.map
QuyueDeGongxuRuheLijieYouxi/js/reader.js
QuyueDeGongxuRuheLijieYouxi/js/reader.js.map
QuyueDeGongxuRuheLijieYouxi/js/reader.min.js
QuyueDeGongxuRuheLijieYouxi/js/reader.min.map
QuyueDeGongxuRuheLijieYouxi/js/hooks/__init__.py
QuyueDeGongxuRuheLijieYouxi/js/hooks/extensions/__init__.py
QuyueDeGongxuRuheLijieYouxi/js/hooks/extensions/highlight.js
QuyueDeGongxuRuheLijieYouxi/js/libs/__init__.py
quyue_de_gongxu_ruhe_lijie_youxi-2024.3.2.0.dist-info/METADATA
quyue_de_gongxu_ruhe_lijie_youxi-2024.3.2.0.dist-info/WHEEL
quyue_de_gongxu_ruhe_lijie_youxi-2024.3.2.0.dist-info/entry_points.txt
quyue_de_gongxu_ruhe_lijie_youxi-2024.3.2.0.dist-info/top_level.txt
quyue_de_gongxu_ruhe_lijie_youxi-2024.3.2.0.dist-info/RECORD
